{"node":{"004f88080944eb1f880ddf6a9be11dab017adab950":{"workers":{"app/(auth)/login/page":{"moduleId":"32178","async":false},"app/forbidden/page":{"moduleId":"32178","async":false},"app/(app)/archivio/page":{"moduleId":"23573","async":false},"app/(app)/dashboard/page":{"moduleId":"23573","async":false},"app/(app)/turni-ferie/page":{"moduleId":"23573","async":false},"app/(app)/logbook/page":{"moduleId":"23573","async":false},"app/(app)/universita/page":{"moduleId":"23573","async":false},"app/(app)/ferie/page":{"moduleId":"23573","async":false},"app/(app)/turni/page":{"moduleId":"23573","async":false},"app/(app)/report/page":{"moduleId":"23573","async":false}},"layer":{"app/(auth)/login/page":"rsc","app/forbidden/page":"rsc","app/(app)/archivio/page":"action-browser","app/(app)/dashboard/page":"action-browser","app/(app)/turni-ferie/page":"action-browser","app/(app)/logbook/page":"action-browser","app/(app)/universita/page":"action-browser","app/(app)/ferie/page":"action-browser","app/(app)/turni/page":"action-browser","app/(app)/report/page":"action-browser"},"filename":"app/(auth)/login/actions.ts","exportedName":"logoutAction"},"40646c0a6e0f6a10bf49c043c413a2a27011031074":{"workers":{"app/(auth)/login/page":{"moduleId":"32178","async":false},"app/forbidden/page":{"moduleId":"32178","async":false},"app/(app)/archivio/page":{"moduleId":"23573","async":false},"app/(app)/dashboard/page":{"moduleId":"23573","async":false},"app/(app)/turni-ferie/page":{"moduleId":"23573","async":false},"app/(app)/logbook/page":{"moduleId":"23573","async":false},"app/(app)/universita/page":{"moduleId":"23573","async":false},"app/(app)/ferie/page":{"moduleId":"23573","async":false},"app/(app)/turni/page":{"moduleId":"23573","async":false},"app/(app)/report/page":{"moduleId":"23573","async":false}},"layer":{"app/(auth)/login/page":"rsc","app/forbidden/page":"rsc","app/(app)/archivio/page":"action-browser","app/(app)/dashboard/page":"action-browser","app/(app)/turni-ferie/page":"action-browser","app/(app)/logbook/page":"action-browser","app/(app)/universita/page":"action-browser","app/(app)/ferie/page":"action-browser","app/(app)/turni/page":"action-browser","app/(app)/report/page":"action-browser"},"filename":"app/(auth)/login/actions.ts","exportedName":"loginAction"},"407b0e871691574d68a9bb870cfdd07ca33c33dbdb":{"workers":{"app/(app)/archivio/page":{"moduleId":"54561","async":false}},"layer":{"app/(app)/archivio/page":"rsc"},"filename":"app/(app)/archivio/actions.ts","exportedName":"uploadLearningPdfAction"},"4061a34703bc014e1dcf311b01cbe425ac3059e594":{"workers":{"app/(app)/logbook/page":{"moduleId":"38242","async":false}},"layer":{"app/(app)/logbook/page":"rsc"},"filename":"app/(app)/logbook/actions.ts","exportedName":"createLogbookEntryAction"},"40edc0814d832fec6cb6d4a52d689eedb081ed207c":{"workers":{"app/(app)/logbook/page":{"moduleId":"38242","async":false}},"layer":{"app/(app)/logbook/page":"rsc"},"filename":"app/(app)/logbook/actions.ts","exportedName":"updateLogbookEntryAction"},"402d56215ab33f9e4134638660569feab21ef253a6":{"workers":{"app/(app)/ferie/page":{"moduleId":"97021","async":false}},"layer":{"app/(app)/ferie/page":"rsc"},"filename":"app/(app)/ferie/actions.ts","exportedName":"updateLeaveRequestAction"},"40360bd328b32d1b649d2ba3ebebe53f61d8fee261":{"workers":{"app/(app)/ferie/page":{"moduleId":"97021","async":false}},"layer":{"app/(app)/ferie/page":"rsc"},"filename":"app/(app)/ferie/actions.ts","exportedName":"approveLeaveRequestAction"},"407270021e3e72787f883673f1a29128e5fef3abea":{"workers":{"app/(app)/ferie/page":{"moduleId":"97021","async":false}},"layer":{"app/(app)/ferie/page":"rsc"},"filename":"app/(app)/ferie/actions.ts","exportedName":"createLeaveRequestAction"},"40e357d2e3f9c030cc3e86cb12c3d2d389f3c2c3dd":{"workers":{"app/(app)/ferie/page":{"moduleId":"97021","async":false}},"layer":{"app/(app)/ferie/page":"rsc"},"filename":"app/(app)/ferie/actions.ts","exportedName":"rejectLeaveRequestAction"}},"edge":{},"encryptionKey":"ApTLkn5uB1oc0xzZvIGlJLO63vhIVXO92+QLrTYXJ1g="}